README.rst
setup.py
src/__init__.py
src/config.py
src/file.py
src/bin/__init__.py
src/bin/versionmanager.py
src/helper/__init__.py
src/helper/console.py
src/parser/__init__.py
src/parser/parser.py
src/parser/regex.py
src/parser/xml.py
tests/__init__.py
tests/test__config.py
tests/test__file.py
tests/test__file_loader.py
tests/parser/__init__.py
tests/parser/test__regex.py
tests/parser/test__xml.py
version_manager.egg-info/PKG-INFO
version_manager.egg-info/SOURCES.txt
version_manager.egg-info/dependency_links.txt
version_manager.egg-info/entry_points.txt
version_manager.egg-info/not-zip-safe
version_manager.egg-info/requires.txt
version_manager.egg-info/top_level.txt