Metadata-Version: 1.0
Name: version-manager
Version: 0.8.5
Summary: Version upgrader in all spesific files like setup.py, package.json, bower.json etc.
Home-page: https://github.com/javrasya/version-manager
Author: Ahmet DAL
Author-email: ceahmetdal@gmail.com
License: BSD
Platform: any
